AUTHORS
CHANGES.rst
LICENSE
MANIFEST.in
README.rst
TODO.md
debian8-dist.sh
setup.py
docs/Makefile
docs/api.rst
docs/api_TODO_MODULE_NAME.rst
docs/conf.py
docs/developer.rst
docs/index.rst
docs/init_sphinx.sh
docs/intro.rst
docs/make.bat
hashutils/__init__.py
hashutils/checksum.py
pyhashutils.egg-info/PKG-INFO
pyhashutils.egg-info/SOURCES.txt
pyhashutils.egg-info/dependency_links.txt
pyhashutils.egg-info/entry_points.txt
pyhashutils.egg-info/top_level.txt