Metadata-Version: 1.1
Name: pyhashutils
Version: 0.1.dev0
Summary: Print or check MD5 and SHA checksums
Home-page: http://www.jdhp.org/software_en.html#hashutils
Author: Jérémie DECOCK
Author-email: jd.jdhp@gmail.com
License: UNKNOWN
Download-URL: http://www.jdhp.org/software_en.html#hashutils
Keywords: hashutils
Platform: UNKNOWN
Classifier: Development Status :: 4 - Beta
Classifier: Intended Audience :: Developers
Classifier: License :: OSI Approved :: MIT License
Classifier: Natural Language :: English
Classifier: Operating System :: OS Independent
Classifier: Programming Language :: Python :: 3
Classifier: Topic :: Software Development :: Libraries
Classifier: Topic :: Software Development :: Libraries :: Python Modules
Classifier: Topic :: Software Development :: Libraries :: Application Frameworks
